django_guardian_on_wheels-1.4.5.dev0.dist-info/DESCRIPTION.rst
django_guardian_on_wheels-1.4.5.dev0.dist-info/LICENSE.txt
django_guardian_on_wheels-1.4.5.dev0.dist-info/METADATA
django_guardian_on_wheels-1.4.5.dev0.dist-info/RECORD
django_guardian_on_wheels-1.4.5.dev0.dist-info/WHEEL
django_guardian_on_wheels-1.4.5.dev0.dist-info/metadata.json
django_guardian_on_wheels-1.4.5.dev0.dist-info/top_level.txt
guardian/__init__.py
guardian/admin.py
guardian/apps.py
guardian/backends.py
guardian/checks.py
guardian/compat.py
guardian/core.py
guardian/decorators.py
guardian/exceptions.py
guardian/forms.py
guardian/managers.py
guardian/mixins.py
guardian/models.py
guardian/shortcuts.py
guardian/utils.py
guardian/conf/__init__.py
guardian/conf/settings.py
guardian/locale/es/LC_MESSAGES/django.mo
guardian/locale/es/LC_MESSAGES/django.po
guardian/locale/fr/LC_MESSAGES/django.mo
guardian/locale/fr/LC_MESSAGES/django.po
guardian/locale/pl/LC_MESSAGES/django.mo
guardian/locale/pl/LC_MESSAGES/django.po
guardian/locale/pt_BR/LC_MESSAGES/django.mo
guardian/locale/pt_BR/LC_MESSAGES/django.po
guardian/locale/ru/LC_MESSAGES/django.mo
guardian/locale/ru/LC_MESSAGES/django.po
guardian/management/__init__.py
guardian/management/commands/__init__.py
guardian/management/commands/clean_orphan_obj_perms.py
guardian/migrations/0001_initial.py
guardian/migrations/__init__.py
guardian/static/guardian/img/icon-no.svg
guardian/static/guardian/img/icon-yes.svg
guardian/templates/admin/guardian/contrib/grappelli/field.html
guardian/templates/admin/guardian/contrib/grappelli/obj_perms_manage.html
guardian/templates/admin/guardian/contrib/grappelli/obj_perms_manage_group.html
guardian/templates/admin/guardian/contrib/grappelli/obj_perms_manage_user.html
guardian/templates/admin/guardian/model/change_form.html
guardian/templates/admin/guardian/model/field.html
guardian/templates/admin/guardian/model/obj_perms_manage.html
guardian/templates/admin/guardian/model/obj_perms_manage_group.html
guardian/templates/admin/guardian/model/obj_perms_manage_user.html
guardian/templates/admin/guardian/model/obj_perms_no.html
guardian/templates/admin/guardian/model/obj_perms_yes.html
guardian/templatetags/__init__.py
guardian/templatetags/guardian_tags.py
guardian/testapp/__init__.py
guardian/testapp/models.py
guardian/testapp/testsettings.py
